csv_identifier/__init__.py
csv_identifier/csv_identifier.py
csv_identifier-0.1.2.dist-info/METADATA
csv_identifier-0.1.2.dist-info/WHEEL
csv_identifier-0.1.2.dist-info/top_level.txt
csv_identifier-0.1.2.dist-info/RECORD
