Metadata-Version: 2.1
Name: csv-identifier
Version: 0.1.2
Summary: A package to read CSV and assign unique IDs to a specified column
Home-page: UNKNOWN
License: UNKNOWN
Platform: UNKNOWN
Classifier: Programming Language :: Python :: 3
Classifier: License :: OSI Approved :: MIT License
Classifier: Operating System :: OS Independent
Requires-Python: >=3.6
Requires-Dist: pandas
Requires-Dist: openpyxl
